tibia_maps/__init__.py
tibia_maps/py.typed
tibia_maps/assets/floor_data/floor-00-map.png
tibia_maps/assets/floor_data/floor-00-path.png
tibia_maps/assets/floor_data/floor-01-map.png
tibia_maps/assets/floor_data/floor-01-path.png
tibia_maps/assets/floor_data/floor-02-map.png
tibia_maps/assets/floor_data/floor-02-path.png
tibia_maps/assets/floor_data/floor-03-map.png
tibia_maps/assets/floor_data/floor-03-path.png
tibia_maps/assets/floor_data/floor-04-map.png
tibia_maps/assets/floor_data/floor-04-path.png
tibia_maps/assets/floor_data/floor-05-map.png
tibia_maps/assets/floor_data/floor-05-path.png
tibia_maps/assets/floor_data/floor-06-map.png
tibia_maps/assets/floor_data/floor-06-path.png
tibia_maps/assets/floor_data/floor-07-map.png
tibia_maps/assets/floor_data/floor-07-path.png
tibia_maps/assets/floor_data/floor-08-map.png
tibia_maps/assets/floor_data/floor-08-path.png
tibia_maps/assets/floor_data/floor-09-map.png
tibia_maps/assets/floor_data/floor-09-path.png
tibia_maps/assets/floor_data/floor-10-map.png
tibia_maps/assets/floor_data/floor-10-path.png
tibia_maps/assets/floor_data/floor-11-map.png
tibia_maps/assets/floor_data/floor-11-path.png
tibia_maps/assets/floor_data/floor-12-map.png
tibia_maps/assets/floor_data/floor-12-path.png
tibia_maps/assets/floor_data/floor-13-map.png
tibia_maps/assets/floor_data/floor-13-path.png
tibia_maps/assets/floor_data/floor-14-map.png
tibia_maps/assets/floor_data/floor-14-path.png
tibia_maps/assets/floor_data/floor-15-map.png
tibia_maps/assets/floor_data/floor-15-path.png
tibia_maps-1.0.1.dist-info/LICENSE
tibia_maps-1.0.1.dist-info/METADATA
tibia_maps-1.0.1.dist-info/WHEEL
tibia_maps-1.0.1.dist-info/top_level.txt
tibia_maps-1.0.1.dist-info/RECORD
