Metadata-Version: 2.1
Name: tibia-maps
Version: 1.0.1
Summary: Floor map data for Tibia
Author-email: Krishant Timilsina <krishtimil@gmail.com>
License: Copyright (c) 2024 Krishant Timilsina
Project-URL: Homepage, https://github.com/krishantt/tibia-maps
Project-URL: Issues, https://github.com/krishantt/tibia-maps/issues
Classifier: Programming Language :: Python :: 3
Requires-Python: >=3
License-File: LICENSE
